mkdocs_pdf_export_plugin/__init__.py
mkdocs_pdf_export_plugin/plugin.py
mkdocs_pdf_export_plugin/renderer.py
mkdocs_pdf_export_plugin/preprocessor/__init__.py
mkdocs_pdf_export_plugin/preprocessor/prep.py
mkdocs_pdf_export_plugin/preprocessor/links/__init__.py
mkdocs_pdf_export_plugin/preprocessor/links/transform.py
mkdocs_pdf_export_plugin/preprocessor/links/util.py
mkdocs_pdf_export_plugin/themes/__init__.py
mkdocs_pdf_export_plugin/themes/cinder.py
mkdocs_pdf_export_plugin/themes/generic.py
mkdocs_pdf_export_plugin/themes/material.py
mkdocs_pdf_export_plugin-0.5.10.dist-info/LICENSE.md
mkdocs_pdf_export_plugin-0.5.10.dist-info/METADATA
mkdocs_pdf_export_plugin-0.5.10.dist-info/WHEEL
mkdocs_pdf_export_plugin-0.5.10.dist-info/entry_points.txt
mkdocs_pdf_export_plugin-0.5.10.dist-info/top_level.txt
mkdocs_pdf_export_plugin-0.5.10.dist-info/RECORD
